archiveis/__init__.py
archiveis/api.py
archiveis-0.0.9.dist-info/LICENSE
archiveis-0.0.9.dist-info/METADATA
archiveis-0.0.9.dist-info/WHEEL
archiveis-0.0.9.dist-info/entry_points.txt
archiveis-0.0.9.dist-info/top_level.txt
archiveis-0.0.9.dist-info/RECORD
