Metadata-Version: 2.1
Name: archiveis
Version: 0.0.9
Summary: A simple Python wrapper for the archive.is capturing service
Home-page: https://www.github.com/pastpages/archiveis/
Author: Ben Welsh
Author-email: ben.welsh@gmail.com
License: MIT
Platform: UNKNOWN
Classifier: Development Status :: 5 - Production/Stable
Classifier: Programming Language :: Python
Classifier: Programming Language :: Python :: 2
Classifier: Programming Language :: Python :: 2.7
Classifier: Programming Language :: Python :: 3
Classifier: Programming Language :: Python :: 3.6
Classifier: Programming Language :: Python :: 3.7
Classifier: License :: OSI Approved :: MIT License
Requires-Dist: requests (>=2.22.0)
Requires-Dist: click
